ros_rosidl_typesupport_fastrtps_cpp-3.8.1.data/data/include/rosidl_typesupport_fastrtps_cpp/rosidl_typesupport_fastrtps_cpp/identifier.hpp
ros_rosidl_typesupport_fastrtps_cpp-3.8.1.data/data/include/rosidl_typesupport_fastrtps_cpp/rosidl_typesupport_fastrtps_cpp/message_type_support.h
ros_rosidl_typesupport_fastrtps_cpp-3.8.1.data/data/include/rosidl_typesupport_fastrtps_cpp/rosidl_typesupport_fastrtps_cpp/message_type_support_decl.hpp
ros_rosidl_typesupport_fastrtps_cpp-3.8.1.data/data/include/rosidl_typesupport_fastrtps_cpp/rosidl_typesupport_fastrtps_cpp/serialization_helpers.hpp
ros_rosidl_typesupport_fastrtps_cpp-3.8.1.data/data/include/rosidl_typesupport_fastrtps_cpp/rosidl_typesupport_fastrtps_cpp/service_type_support.h
ros_rosidl_typesupport_fastrtps_cpp-3.8.1.data/data/include/rosidl_typesupport_fastrtps_cpp/rosidl_typesupport_fastrtps_cpp/service_type_support_decl.hpp
ros_rosidl_typesupport_fastrtps_cpp-3.8.1.data/data/include/rosidl_typesupport_fastrtps_cpp/rosidl_typesupport_fastrtps_cpp/visibility_control.h
ros_rosidl_typesupport_fastrtps_cpp-3.8.1.data/data/include/rosidl_typesupport_fastrtps_cpp/rosidl_typesupport_fastrtps_cpp/wstring_conversion.hpp
ros_rosidl_typesupport_fastrtps_cpp-3.8.1.data/data/lib/librosidl_typesupport_fastrtps_cpp.so
ros_rosidl_typesupport_fastrtps_cpp-3.8.1.data/data/lib/python3.13/site-packages/rosidl_typesupport_fastrtps_cpp/__init__.py
ros_rosidl_typesupport_fastrtps_cpp-3.8.1.data/data/lib/python3.13/site-packages/rosidl_typesupport_fastrtps_cpp/cli.py
ros_rosidl_typesupport_fastrtps_cpp-3.8.1.data/data/lib/python3.13/site-packages/rosidl_typesupport_fastrtps_cpp/__pycache__/__init__.cpython-313.pyc
ros_rosidl_typesupport_fastrtps_cpp-3.8.1.data/data/lib/python3.13/site-packages/rosidl_typesupport_fastrtps_cpp/__pycache__/cli.cpython-313.pyc
ros_rosidl_typesupport_fastrtps_cpp-3.8.1.data/data/lib/python3.13/site-packages/rosidl_typesupport_fastrtps_cpp-3.8.1-py3.13.egg-info/PKG-INFO
ros_rosidl_typesupport_fastrtps_cpp-3.8.1.data/data/lib/python3.13/site-packages/rosidl_typesupport_fastrtps_cpp-3.8.1-py3.13.egg-info/SOURCES.txt
ros_rosidl_typesupport_fastrtps_cpp-3.8.1.data/data/lib/python3.13/site-packages/rosidl_typesupport_fastrtps_cpp-3.8.1-py3.13.egg-info/dependency_links.txt
ros_rosidl_typesupport_fastrtps_cpp-3.8.1.data/data/lib/python3.13/site-packages/rosidl_typesupport_fastrtps_cpp-3.8.1-py3.13.egg-info/entry_points.txt
ros_rosidl_typesupport_fastrtps_cpp-3.8.1.data/data/lib/python3.13/site-packages/rosidl_typesupport_fastrtps_cpp-3.8.1-py3.13.egg-info/top_level.txt
ros_rosidl_typesupport_fastrtps_cpp-3.8.1.data/data/lib/rosidl_typesupport_fastrtps_cpp/rosidl_typesupport_fastrtps_cpp
ros_rosidl_typesupport_fastrtps_cpp-3.8.1.dist-info/METADATA
ros_rosidl_typesupport_fastrtps_cpp-3.8.1.dist-info/WHEEL
ros_rosidl_typesupport_fastrtps_cpp-3.8.1.dist-info/entry_points.txt
ros_rosidl_typesupport_fastrtps_cpp-3.8.1.dist-info/top_level.txt
ros_rosidl_typesupport_fastrtps_cpp-3.8.1.dist-info/RECORD
